py.typed
codat_common/__init__.py
codat_common/_hooks/__init__.py
codat_common/_hooks/registration.py
codat_common/_hooks/sdkhooks.py
codat_common/_hooks/types.py
codat_common/basesdk.py
codat_common/companies_sdk.py
codat_common/connection_management.py
codat_common/connections_sdk.py
codat_common/cors_settings.py
codat_common/custom_data_type.py
codat_common/groups_sdk.py
codat_common/httpclient.py
codat_common/integrations_sdk.py
codat_common/models/__init__.py
codat_common/models/add_company_to_groupop.py
codat_common/models/apikeydetails.py
codat_common/models/apikeys.py
codat_common/models/branding.py
codat_common/models/brandingbutton.py
codat_common/models/brandingimage.py
codat_common/models/brandinglogo.py
codat_common/models/clientratelimitreachedwebhook.py
codat_common/models/clientratelimitreachedwebhookdata.py
codat_common/models/clientratelimitresetwebhook.py
codat_common/models/clientratelimitresetwebhookdata.py
codat_common/models/clientratelimitwebhook.py
codat_common/models/clientratelimitwebhookpayload.py
codat_common/models/companies.py
codat_common/models/company.py
codat_common/models/companydetails.py
codat_common/models/companygroupassignment.py
codat_common/models/companyreference.py
codat_common/models/companyrequestbody.py
codat_common/models/companywebhook.py
codat_common/models/configure_custom_data_typeop.py
codat_common/models/configure_supplemental_dataop.py
codat_common/models/connection.py
codat_common/models/connectionmanagementaccesstoken.py
codat_common/models/connectionmanagementallowedorigins.py
codat_common/models/connections.py
codat_common/models/connectionstatuschangedwebhook.py
codat_common/models/connectionstatuschangedwebhookdata.py
codat_common/models/create_connectionop.py
codat_common/models/createapikey.py
codat_common/models/createrule.py
codat_common/models/customdatatypeconfiguration.py
codat_common/models/customdatatyperecord.py
codat_common/models/customdatatyperecords.py
codat_common-0.35.0.dist-info/METADATA
codat_common-0.35.0.dist-info/WHEEL
codat_common-0.35.0.dist-info/RECORD
